magma_database/__init__.py
magma_database/config.py
magma_database/database.py
magma_database/helper.py
magma_database/models/__init__.py
magma_database/models/base.py
magma_database/models/mounts.py
magma_database/models/rsam_csv.py
magma_database/models/sds.py
magma_database/models/station.py
magma_database/models/volcano.py
magma_database/models/winston_scnl.py
magma_database/resources/.env.local.example
magma_database/resources/__init__.py
magma_database/resources/channels.xlsx
magma_database/resources/volcanoes.xlsx
magma_database-1.5.0.dist-info/licenses/LICENSE
magma_database-1.5.0.dist-info/WHEEL
magma_database-1.5.0.dist-info/METADATA
magma_database-1.5.0.dist-info/RECORD
