Metadata-Version: 2.4
Name: magma-database
Version: 1.5.0
Summary: Database foundation for MAGMA packages.
Keywords: magma,magma-indonesia,volcanology,volcano,seismic,database
Author-email: Martanto <martanto@live.com>, Devy Kamil Syahbana <devy.syahbana@gmail.com>, Syarif Abdul Manaf <riefmof@gmail.com>
Requires-Python: >=3.11
Classifier: License :: OSI Approved :: MIT License
Classifier: Operating System :: OS Independent
Classifier: Programming Language :: Python :: 3.11
Classifier: Programming Language :: Python :: 3.12
License-File: LICENSE
Requires-Dist: openpyxl>=3.1.0
Requires-Dist: numpy>=2.0.0
Requires-Dist: pandas>=2.2.2
Requires-Dist: cryptography>=43.0.0
Requires-Dist: pymysql>=1.1.0
Requires-Dist: peewee>=3.17.5
Requires-Dist: importlib-resources
Requires-Dist: python-dotenv>=1.0.1
Requires-Dist: openpyxl ; extra == "base"
Requires-Dist: numpy ; extra == "base"
Requires-Dist: pandas ; extra == "base"
Requires-Dist: cryptography ; extra == "base"
Requires-Dist: pymysql ; extra == "base"
Requires-Dist: peewee ; extra == "base"
Requires-Dist: importlib-resources ; extra == "base"
Requires-Dist: python-dotenv ; extra == "base"
Project-URL: Homepage, https://github.com/martanto/magma-database
Project-URL: Issues, https://github.com/martanto/magma-database/issues
Provides-Extra: base
